onebone/__init__.py
onebone/feature/__init__.py
onebone/feature/correlations.py
onebone/feature/frequency.py
onebone/feature/gear.py
onebone/feature/snr.py
onebone/feature/tacho.py
onebone/feature/tacholess.py
onebone/feature/time.py
onebone/math/__init__.py
onebone/math/integrate.py
onebone/preprocessing/__init__.py
onebone/preprocessing/feature_selection.py
onebone/preprocessing/pd.py
onebone/preprocessing/scaling.py
onebone/signal/__init__.py
onebone/signal/denoise.py
onebone/signal/envelope.py
onebone/signal/fft.py
onebone/signal/filter.py
onebone/signal/smoothing.py
onebone/utils/__init__.py
onebone/utils/slicing.py
onebone/utils/timer.py
onebone-1.3.1.dist-info/WHEEL
onebone-1.3.1.dist-info/METADATA
onebone-1.3.1.dist-info/RECORD
