Metadata-Version: 2.1
Name: onebone
Version: 1.3.1
Summary: An Open Source Signal Processing Library for Sensor Signals about vibration, current, etc.
Author: Kyunghwan Kim
Author-email: kyunghwan.kim@onepredict.com
Requires-Python: >=3.8,<3.11
Classifier: Programming Language :: Python :: 3
Classifier: Programming Language :: Python :: 3.10
Classifier: Programming Language :: Python :: 3.8
Classifier: Programming Language :: Python :: 3.9
Requires-Dist: PyWavelets (>=1.3.0,<2.0.0)
Requires-Dist: numpy (>=1.23.0,<2.0.0)
Requires-Dist: pandas (>=1.4.3,<2.0.0)
Requires-Dist: scikit-learn (>=1.2.2,<2.0.0)
Requires-Dist: scipy (>=1.8.1,<2.0.0)
